setup.py
pymysql_sa/__init__.py
pymysql_sa/base.py
pymysql_sa.egg-info/PKG-INFO
pymysql_sa.egg-info/SOURCES.txt
pymysql_sa.egg-info/dependency_links.txt
pymysql_sa.egg-info/entry_points.txt
pymysql_sa.egg-info/requires.txt
pymysql_sa.egg-info/top_level.txt
pymysql_sa/tests/__init__.py