Metadata-Version: 1.0
Name: pymysql-sa
Version: 1.0
Summary: PyMySQL dialect for SQLAlchemy.
Home-page: http://www.evax.fr
Author: Evax Software
Author-email: contact@evax.fr
License: MIT License
Keywords: sqlalchemy,pymysql,dialect,gevent
Platform: UNKNOWN
Classifier: Development Status :: 5 - Production/Stable
Classifier: Intended Audience :: Developers
Classifier: License :: OSI Approved :: MIT License
Classifier: Programming Language :: Python
Classifier: Topic :: Database :: Front-Ends
Classifier: Operating System :: OS Independent
